s3lfs/__init__.py
s3lfs/cli.py
s3lfs/core.py
s3lfs/metrics.py
s3lfs/path_resolver.py
s3lfs/utils.py
s3lfs-0.1.0.dist-info/METADATA
s3lfs-0.1.0.dist-info/WHEEL
s3lfs-0.1.0.dist-info/entry_points.txt
s3lfs-0.1.0.dist-info/licenses/LICENSE
s3lfs-0.1.0.dist-info/RECORD
