Metadata-Version: 2.4
Name: s3lfs
Version: 0.1.0
Summary: A Python-based version control system for large assets using Amazon S3.
Project-URL: Homepage, https://github.com/kmatzen/s3lfs
Project-URL: Repository, https://github.com/kmatzen/s3lfs
Project-URL: Documentation, https://github.com/kmatzen/s3lfs#readme
Project-URL: Bug Tracker, https://github.com/kmatzen/s3lfs/issues
Project-URL: Changelog, https://github.com/kmatzen/s3lfs/blob/main/CHANGELOG.md
Author-email: Kevin Blackburn-Matzen <kmatzen@gmail.com>
License: MIT
License-File: LICENSE
Keywords: aws,git,large-files,lfs,s3,storage,version-control
Classifier: Development Status :: 4 - Beta
Classifier: Environment :: Console
Classifier: Intended Audience :: Developers
Classifier: License :: OSI Approved :: MIT License
Classifier: Operating System :: OS Independent
Classifier: Programming Language :: Python :: 3
Classifier: Programming Language :: Python :: 3.9
Classifier: Programming Language :: Python :: 3.10
Classifier: Programming Language :: Python :: 3.11
Classifier: Programming Language :: Python :: 3.12
Classifier: Topic :: Software Development :: Version Control
Classifier: Topic :: System :: Archiving
Classifier: Typing :: Typed
Requires-Python: >=3.9
Requires-Dist: boto3>=1.28.0
Requires-Dist: click>=8.1.8
Requires-Dist: portalocker>=3.1.1
Requires-Dist: pyyaml>=6.0
Requires-Dist: tqdm>=4.64.0
